 16           0 LOAD_FAST                0 (command)
              2 LOAD_METHOD              0 (split)
              4 CALL_METHOD              0

 17           6 DUP_TOP
              8 DUP_TOP
             10 MATCH_SEQUENCE
             12 POP_JUMP_IF_FALSE       16 (to 32)
             14 GET_LEN
             16 LOAD_CONST               1 (1)
             18 COMPARE_OP               2 (==)
             20 POP_JUMP_IF_FALSE       16 (to 32)
             22 UNPACK_SEQUENCE          1
             24 LOAD_CONST               2 ('north')
             26 COMPARE_OP               2 (==)
             28 POP_JUMP_IF_FALSE       17 (to 34)
             30 JUMP_FORWARD            19 (to 70)
        >>   32 POP_TOP
        >>   34 DUP_TOP
             36 MATCH_SEQUENCE
             38 POP_JUMP_IF_FALSE       32 (to 64)
             40 GET_LEN
             42 LOAD_CONST               3 (2)
             44 COMPARE_OP               2 (==)
             46 POP_JUMP_IF_FALSE       32 (to 64)
             48 UNPACK_SEQUENCE          2
             50 LOAD_CONST               4 ('go')
             52 COMPARE_OP               2 (==)
             54 POP_JUMP_IF_FALSE       32 (to 64)
             56 LOAD_CONST               2 ('north')
             58 COMPARE_OP               2 (==)
             60 POP_JUMP_IF_FALSE       33 (to 66)
             62 JUMP_FORWARD             3 (to 70)
        >>   64 POP_TOP
        >>   66 POP_TOP
             68 JUMP_FORWARD            10 (to 90)
        >>   70 POP_TOP
             72 POP_TOP

 18          74 LOAD_GLOBAL              1 (print)
             76 LOAD_CONST               2 ('north')
             78 CALL_FUNCTION            1
             80 POP_TOP

 21          82 LOAD_GLOBAL              2 (match_command)
             84 LOAD_FAST                0 (command)
             86 CALL_FUNCTION            1
             88 RETURN_VALUE

 19     >>   90 DUP_TOP
             92 MATCH_SEQUENCE
             94 POP_JUMP_IF_FALSE       57 (to 114)
             96 GET_LEN
             98 LOAD_CONST               3 (2)
            100 COMPARE_OP               2 (==)
            102 POP_JUMP_IF_FALSE       57 (to 114)
            104 UNPACK_SEQUENCE          2
            106 LOAD_CONST               5 ('get')
            108 COMPARE_OP               2 (==)
            110 POP_JUMP_IF_FALSE       57 (to 114)
            112 JUMP_FORWARD            41 (to 196)
        >>  114 POP_TOP
            116 DUP_TOP
            118 MATCH_SEQUENCE
            120 POP_JUMP_IF_FALSE       74 (to 148)
            122 GET_LEN
            124 LOAD_CONST               6 (3)
            126 COMPARE_OP               2 (==)
            128 POP_JUMP_IF_FALSE       74 (to 148)
            130 UNPACK_SEQUENCE          3
            132 LOAD_CONST               7 ('pick')
            134 COMPARE_OP               2 (==)
            136 POP_JUMP_IF_FALSE       73 (to 146)
            138 LOAD_CONST               8 ('up')
            140 COMPARE_OP               2 (==)
            142 POP_JUMP_IF_FALSE       74 (to 148)
            144 JUMP_FORWARD            25 (to 196)
        >>  146 POP_TOP
        >>  148 POP_TOP
            150 DUP_TOP
            152 MATCH_SEQUENCE
            154 POP_JUMP_IF_FALSE       92 (to 184)
            156 GET_LEN
            158 LOAD_CONST               6 (3)
            160 COMPARE_OP               2 (==)
            162 POP_JUMP_IF_FALSE       92 (to 184)
            164 UNPACK_SEQUENCE          3
            166 LOAD_CONST               7 ('pick')
            168 COMPARE_OP               2 (==)
            170 POP_JUMP_IF_FALSE       91 (to 182)
            172 ROT_TWO
            174 LOAD_CONST               8 ('up')
            176 COMPARE_OP               2 (==)
            178 POP_JUMP_IF_FALSE       92 (to 184)
            180 JUMP_FORWARD             7 (to 196)
        >>  182 POP_TOP
        >>  184 POP_TOP
            186 POP_TOP

 21         188 LOAD_GLOBAL              2 (match_command)
            190 LOAD_FAST                0 (command)
            192 CALL_FUNCTION            1
            194 RETURN_VALUE

 19     >>  196 ROT_TWO
            198 POP_TOP
            200 STORE_FAST               1 (obj)

 20         202 LOAD_GLOBAL              1 (print)
            204 LOAD_CONST               9 ('pick up')
            206 LOAD_FAST                1 (obj)
            208 CALL_FUNCTION            2
            210 POP_TOP

 21         212 LOAD_GLOBAL              2 (match_command)
            214 LOAD_FAST                0 (command)
            216 CALL_FUNCTION            1
            218 RETURN_VALUE
